tweek/__init__.py
tweek/cli.py
tweek/cli_helpers.py
tweek/diagnostics.py
tweek/licensing.py
tweek/config/__init__.py
tweek/config/allowed_dirs.yaml
tweek/config/manager.py
tweek/config/patterns.yaml
tweek/config/tiers.yaml
tweek/hooks/__init__.py
tweek/hooks/pre_tool_use.py
tweek/integrations/__init__.py
tweek/integrations/moltbot.py
tweek/logging/__init__.py
tweek/logging/bundle.py
tweek/logging/json_logger.py
tweek/logging/security_log.py
tweek/mcp/__init__.py
tweek/mcp/approval.py
tweek/mcp/approval_cli.py
tweek/mcp/proxy.py
tweek/mcp/screening.py
tweek/mcp/server.py
tweek/mcp/clients/__init__.py
tweek/mcp/clients/chatgpt.py
tweek/mcp/clients/claude_desktop.py
tweek/mcp/clients/gemini.py
tweek/platform/__init__.py
tweek/plugins/__init__.py
tweek/plugins/base.py
tweek/plugins/git_discovery.py
tweek/plugins/git_installer.py
tweek/plugins/git_lockfile.py
tweek/plugins/git_registry.py
tweek/plugins/git_security.py
tweek/plugins/scope.py
tweek/plugins/compliance/__init__.py
tweek/plugins/compliance/gdpr.py
tweek/plugins/compliance/gov.py
tweek/plugins/compliance/hipaa.py
tweek/plugins/compliance/legal.py
tweek/plugins/compliance/pci.py
tweek/plugins/compliance/soc2.py
tweek/plugins/detectors/__init__.py
tweek/plugins/detectors/continue_dev.py
tweek/plugins/detectors/copilot.py
tweek/plugins/detectors/cursor.py
tweek/plugins/detectors/moltbot.py
tweek/plugins/detectors/windsurf.py
tweek/plugins/providers/__init__.py
tweek/plugins/providers/anthropic.py
tweek/plugins/providers/azure_openai.py
tweek/plugins/providers/bedrock.py
tweek/plugins/providers/google.py
tweek/plugins/providers/openai.py
tweek/plugins/screening/__init__.py
tweek/plugins/screening/llm_reviewer.py
tweek/plugins/screening/pattern_matcher.py
tweek/plugins/screening/rate_limiter.py
tweek/plugins/screening/session_analyzer.py
tweek/proxy/__init__.py
tweek/proxy/addon.py
tweek/proxy/interceptor.py
tweek/proxy/server.py
tweek/sandbox/__init__.py
tweek/sandbox/executor.py
tweek/sandbox/linux.py
tweek-0.1.0.dist-info/licenses/LICENSE
tweek-0.1.0.dist-info/METADATA
tweek-0.1.0.dist-info/WHEEL
tweek-0.1.0.dist-info/entry_points.txt
tweek-0.1.0.dist-info/top_level.txt
tweek-0.1.0.dist-info/RECORD
