Metadata-Version: 2.4
Name: tweek
Version: 0.1.0
Summary: Defense-in-depth security for AI coding assistants - protect credentials, code, and system from prompt injection attacks
Author: Tommy Mancino
License-Expression: Apache-2.0
Project-URL: Homepage, https://gettweek.com
Project-URL: Repository, https://github.com/gettweek/tweek
Project-URL: Issues, https://github.com/gettweek/tweek/issues
Keywords: claude,security,sandbox,ai,llm,tweek,claude-code,prompt-injection,mcp,credential-theft
Classifier: Development Status :: 4 - Beta
Classifier: Intended Audience :: Developers
Classifier: Operating System :: MacOS :: MacOS X
Classifier: Operating System :: POSIX :: Linux
Classifier: Operating System :: Microsoft :: Windows
Classifier: Programming Language :: Python :: 3.11
Classifier: Programming Language :: Python :: 3.12
Classifier: Topic :: Security
Classifier: Topic :: Software Development :: Quality Assurance
Requires-Python: >=3.11
License-File: LICENSE
Requires-Dist: click>=8.0
Requires-Dist: pyyaml>=6.0
Requires-Dist: rich>=13.0
Requires-Dist: keyring>=25.0
Provides-Extra: llm
Requires-Dist: anthropic>=0.18.0; extra == "llm"
Provides-Extra: linux
Requires-Dist: secretstorage>=3.0; extra == "linux"
Provides-Extra: mcp
Requires-Dist: mcp>=1.0.0; extra == "mcp"
Provides-Extra: proxy
Requires-Dist: mitmproxy>=10.0; extra == "proxy"
Provides-Extra: dev
Requires-Dist: pytest>=7.0; extra == "dev"
Requires-Dist: pytest-cov>=4.0; extra == "dev"
Requires-Dist: black>=23.0; extra == "dev"
Requires-Dist: ruff>=0.1.0; extra == "dev"
Requires-Dist: twine>=4.0; extra == "dev"
Requires-Dist: build>=1.0; extra == "dev"
Provides-Extra: all
Requires-Dist: tweek[llm,mcp,proxy]; extra == "all"
Dynamic: license-file
